LICENSE
make_env/__init__.py
make_env/__main__.py
make.env-0.0.7.dist-info/entry_points.txt
make.env-0.0.7.dist-info/LICENSE
make.env-0.0.7.dist-info/WHEEL
make.env-0.0.7.dist-info/METADATA
make.env-0.0.7.dist-info/RECORD
